tin/__init__.py
tin/api.py
tin/auth.py
tin/base.py
tin/config.py
tin/exceptions.py
tin/models.py
tin/response.py
tin/version.py
tin-1.3.6.dist-info/LICENSE
tin-1.3.6.dist-info/WHEEL
tin-1.3.6.dist-info/METADATA
tin-1.3.6.dist-info/RECORD
