Metadata-Version: 2.1
Name: tin
Version: 1.3.6
Summary: Tin is a thin, configurable wrapper around requests, to interact with
Author-email: Mike Culbertson <_fsck@itsdown.org>
Requires-Python: >=3.6
Classifier: Development Status :: 4 - Beta
Classifier: Environment :: Console
Classifier: Environment :: Web Environment
Classifier: License :: OSI Approved :: Apache Software License
Classifier: Programming Language :: Python :: 3
Classifier: Programming Language :: Python :: 3 :: Only
Requires-Dist: requests~=2.22.0
Requires-Dist: simplejson~=3.17.2
Requires-Dist: pyyaml>=5.4
Requires-Dist: deepmerge~=0.3.0
Project-URL: Home, https://gitlab.com/explody/tin
